{
  "date": "2026-07-15",
  "mobile": {
    "performance": 36,
    "seo": 77,
    "accessibility": 81,
    "bestPractices": 71,
    "lcp": "5.7 s",
    "fcp": "3.8 s",
    "cls": "0.002",
    "speedIndex": "6.8 s",
    "lcpMs": 5727.286,
    "fcpMs": 3848.3860000000004,
    "clsValue": 0.001610843019784437,
    "speedIndexMs": 6797.736926920072,
    "performanceStatus": "bad",
    "seoStatus": "mid",
    "accessibilityStatus": "mid",
    "bestPracticesStatus": "mid",
    "previousPerformance": 33,
    "performanceDelta": 3,
    "performanceDeltaText": "↑ +3 puan yükseldi",
    "performanceDeltaClass": "delta-up"
  },
  "desktop": {
    "performance": 60,
    "seo": 77,
    "accessibility": 79,
    "bestPractices": 74,
    "lcp": "3.2 s",
    "fcp": "1.3 s",
    "cls": "0.176",
    "speedIndex": "2.2 s",
    "lcpMs": 3235.9984999999997,
    "fcpMs": 1322.2144999999998,
    "clsValue": 0.17646190680071916,
    "speedIndexMs": 2202.9918766233473,
    "performanceStatus": "mid",
    "seoStatus": "mid",
    "accessibilityStatus": "mid",
    "bestPracticesStatus": "mid",
    "previousPerformance": 75,
    "performanceDelta": -15,
    "performanceDeltaText": "↓ -15 puan düştü",
    "performanceDeltaClass": "delta-down"
  },
  "overallScore": 56,
  "healthStatus": "bad",
  "healthLabel": "CRITICAL",
  "healthText": "Genel sağlık kritik seviyede. Özellikle mobil performans, LCP ve sayfa açılış hızı öncelikli aksiyon gerektiriyor.",
  "mobileTrendText": "33 → 34 → 34 → 31 → 33 → 33 → 36",
  "desktopTrendText": "74 → 80 → 76 → 59 → 64 → 75 → 60",
  "mobileTrendBars": "▃ ▃ ▃ ▃ ▃ ▃ ▃",
  "desktopTrendBars": "▅ ▆ ▆ ▄ ▅ ▆ ▅",
  "aiComment": "⚠ Mobil performans düşük seviyede; reklam trafiği ve satış dönüşümü açısından öncelikli risk alanı.<br>⚠ Desktop tarafında da performans iyileştirme alanı var.<br>⚠ Mobile LCP yüksek; ana görsel, banner, font ve render-blocking kaynaklar incelenmeli.<br>⚠ FCP gecikiyor; ilk ekrana gelen CSS/JS yükleri azaltılmalı.<br>✓ CLS iyi seviyede; sayfa açılırken görsel kayması ciddi bir problem oluşturmuyor.",
  "actionOne": "Mobil LCP için ana banner/görseller WebP veya AVIF formatında optimize edilmeli.",
  "actionTwo": "İlk açılışta yüklenen CSS ve JavaScript dosyaları azaltılmalı veya ertelenmeli.",
  "actionThree": "Mobil performans için kullanılmayan JavaScript, üçüncü parti scriptler ve ağır uygulama kaynakları kontrol edilmeli."
}